src/__init__.py
src/client.py
src/cognee_client.py
src/server.py
src/test_client.py
src/codingagents/__init__.py
src/codingagents/coding_rule_associations.py
iflow_mcp_topoteretes_cognee_mcp-0.5.0.dist-info/METADATA
iflow_mcp_topoteretes_cognee_mcp-0.5.0.dist-info/WHEEL
iflow_mcp_topoteretes_cognee_mcp-0.5.0.dist-info/entry_points.txt
iflow_mcp_topoteretes_cognee_mcp-0.5.0.dist-info/RECORD
