Metadata-Version: 2.4
Name: iflow-mcp_topoteretes_cognee-mcp
Version: 0.5.0
Summary: Cognee MCP server
Author-email: Boris Arzentar <boris@topoteretes.com>, Igor Ilic <igor@topoteretes.com>, Laszlo Hajdu <laszlo@topoteretes.com>
Requires-Python: >=3.10
Requires-Dist: cognee==0.5.0
Requires-Dist: fastmcp<3.0.0,>=2.10.0
Requires-Dist: httpx<1.0.0,>=0.27.0
Requires-Dist: mcp<2.0.0,>=1.12.0
Requires-Dist: uv<1.0.0,>=0.6.3
